odoo/addons/stock_picking_batch_extended_account_sale_type/__init__.py
odoo/addons/stock_picking_batch_extended_account_sale_type/__manifest__.py
odoo/addons/stock_picking_batch_extended_account_sale_type/i18n/es.po
odoo/addons/stock_picking_batch_extended_account_sale_type/i18n/stock_picking_batch_extended_account_sale_type.pot
odoo/addons/stock_picking_batch_extended_account_sale_type/models/__init__.py
odoo/addons/stock_picking_batch_extended_account_sale_type/models/res_partner.py
odoo/addons/stock_picking_batch_extended_account_sale_type/models/sale_order_type.py
odoo/addons/stock_picking_batch_extended_account_sale_type/models/stock_batch_picking.py
odoo/addons/stock_picking_batch_extended_account_sale_type/static/description/icon.png
odoo/addons/stock_picking_batch_extended_account_sale_type/tests/__init__.py
odoo/addons/stock_picking_batch_extended_account_sale_type/tests/test_stock_picking_batch_extended_account_sale_type.py
odoo/addons/stock_picking_batch_extended_account_sale_type/views/sale_order_type_views.xml
odoo13_addon_stock_picking_batch_extended_account_sale_type-13.0.1.0.1.dev2.dist-info/METADATA
odoo13_addon_stock_picking_batch_extended_account_sale_type-13.0.1.0.1.dev2.dist-info/WHEEL
odoo13_addon_stock_picking_batch_extended_account_sale_type-13.0.1.0.1.dev2.dist-info/top_level.txt
odoo13_addon_stock_picking_batch_extended_account_sale_type-13.0.1.0.1.dev2.dist-info/RECORD
